jqdata.py
bullet_trade/__init__.py
bullet_trade/__main__.py
bullet_trade/__version__.py
bullet_trade/broker/__init__.py
bullet_trade/broker/base.py
bullet_trade/broker/qmt.py
bullet_trade/broker/qmt_remote.py
bullet_trade/broker/simulator.py
bullet_trade/cli/__init__.py
bullet_trade/cli/backtest.py
bullet_trade/cli/jupyterlab.py
bullet_trade/cli/live.py
bullet_trade/cli/main.py
bullet_trade/cli/optimize.py
bullet_trade/cli/report.py
bullet_trade/compat/__init__.py
bullet_trade/compat/jqdata.py
bullet_trade/core/__init__.py
bullet_trade/core/analysis.py
bullet_trade/core/api.py
bullet_trade/core/async_engine.py
bullet_trade/core/async_scheduler.py
bullet_trade/core/engine.py
bullet_trade/core/event_bus.py
bullet_trade/core/event_loop.py
bullet_trade/core/events.py
bullet_trade/core/exceptions.py
bullet_trade/core/globals.py
bullet_trade/core/live_engine.py
bullet_trade/core/live_runtime.py
bullet_trade/core/message.py
bullet_trade/core/models.py
bullet_trade/core/notifications.py
bullet_trade/core/optimizer.py
bullet_trade/core/orders.py
bullet_trade/core/pricing.py
bullet_trade/core/risk_control.py
bullet_trade/core/runtime.py
bullet_trade/core/scheduler.py
bullet_trade/core/settings.py
bullet_trade/data/__init__.py
bullet_trade/data/api.py
bullet_trade/data/base.py
bullet_trade/data/cache.py
bullet_trade/data/providers/base.py
bullet_trade/data/providers/jqdata.py
bullet_trade/data/providers/miniqmt.py
bullet_trade/data/providers/remote_qmt.py
bullet_trade/data/providers/tushare.py
bullet_trade/notebook/01.welcome.ipynb
bullet_trade/notebook/02.example.ipynb
bullet_trade/notebook/03.data.ipynb
bullet_trade/notebook/04.joinquant_remote_live_trade.ipynb
bullet_trade/notebook/__init__.py
bullet_trade/remote/__init__.py
bullet_trade/remote/connection.py
bullet_trade/reporting/__init__.py
bullet_trade/reporting/templates/__init__.py
bullet_trade/reporting/templates/default.html
bullet_trade/research/io.py
bullet_trade/server/__init__.py
bullet_trade/server/app.py
bullet_trade-0.6.0.dist-info/licenses/LICENSE
bullet_trade-0.6.0.dist-info/METADATA
bullet_trade-0.6.0.dist-info/WHEEL
bullet_trade-0.6.0.dist-info/entry_points.txt
bullet_trade-0.6.0.dist-info/top_level.txt
bullet_trade-0.6.0.dist-info/RECORD
