Metadata-Version: 2.4
Name: bullet-trade
Version: 0.6.0
Summary: BulletTrade - 专业的量化交易系统，兼容聚宽策略，支持多数据源和实盘交易
Author-email: BulletTrade Team <bullettrade.cn@gmail.com>
License: MIT
Project-URL: Homepage, https://github.com/BulletTrade/bullet-trade
Project-URL: Documentation, https://bullettrade.readthedocs.io
Project-URL: Repository, https://github.com/BulletTrade/bullet-trade
Project-URL: Changelog, https://github.com/BulletTrade/bullet-trade/blob/main/CHANGELOG.md
Keywords: 量化交易,quantitative trading,backtest,聚宽,joinquant,algotrading,stock trading,live trading
Classifier: Development Status :: 4 - Beta
Classifier: Intended Audience :: Financial and Insurance Industry
Classifier: Intended Audience :: Developers
Classifier: License :: OSI Approved :: MIT License
Classifier: Programming Language :: Python :: 3
Classifier: Programming Language :: Python :: 3.8
Classifier: Programming Language :: Python :: 3.9
Classifier: Programming Language :: Python :: 3.10
Classifier: Programming Language :: Python :: 3.11
Classifier: Programming Language :: Python :: 3.12
Classifier: Topic :: Office/Business :: Financial :: Investment
Classifier: Topic :: Software Development :: Libraries :: Python Modules
Requires-Python: >=3.8
License-File: LICENSE
Requires-Dist: pandas>=1.3.0
Requires-Dist: numpy>=1.21.0
Requires-Dist: matplotlib>=3.4.0
Requires-Dist: jqdatasdk>=1.8.0
Requires-Dist: plotly>=5.15.0
Requires-Dist: python-dotenv>=0.19.0
Requires-Dist: pyecharts>=1.9.0
Requires-Dist: tabulate>=0.9.0
Requires-Dist: jupyterlab>=4.1.0
Requires-Dist: ipykernel>=6.29.0
Provides-Extra: dev
Requires-Dist: pytest>=7.0.0; extra == "dev"
Requires-Dist: pytest-cov>=3.0.0; extra == "dev"
Requires-Dist: pytest-mock>=3.6.0; extra == "dev"
Requires-Dist: pytest-asyncio>=0.21.0; extra == "dev"
Requires-Dist: pyyaml>=6.0; extra == "dev"
Requires-Dist: black>=22.0.0; extra == "dev"
Requires-Dist: flake8>=4.0.0; extra == "dev"
Requires-Dist: mypy>=0.950; extra == "dev"
Requires-Dist: isort>=5.10.0; extra == "dev"
Provides-Extra: tushare
Requires-Dist: tushare>=1.2.0; extra == "tushare"
Provides-Extra: qmt
Requires-Dist: xtquant>=1.0.0; extra == "qmt"
Provides-Extra: qmtserver
Requires-Dist: pywin32>=305; platform_system == "Windows" and extra == "qmtserver"
Provides-Extra: report
Requires-Dist: snapshot-selenium>=0.0.3; extra == "report"
Requires-Dist: selenium>=4.10.0; extra == "report"
Requires-Dist: chromedriver-autoinstaller>=0.6.0; extra == "report"
Requires-Dist: snapshot-phantomjs>=0.0.3; extra == "report"
Provides-Extra: all
Requires-Dist: bullet-trade[dev,qmt,qmtserver,report,tushare]; extra == "all"
Dynamic: license-file
